MANIFEST.in
README.md
README.rst
pyproject.toml
setup.py
django_froala_editor.egg-info/PKG-INFO
django_froala_editor.egg-info/SOURCES.txt
django_froala_editor.egg-info/dependency_links.txt
django_froala_editor.egg-info/not-zip-safe
django_froala_editor.egg-info/top_level.txt
froala_editor/__init__.py
froala_editor/fields.py
froala_editor/urls.py
froala_editor/views.py
froala_editor/widgets.py
froala_editor/static/.DS_Store
froala_editor/static/froala_editor/.DS_Store
froala_editor/static/froala_editor/css/.DS_Store
froala_editor/static/froala_editor/css/froala-django.css
froala_editor/static/froala_editor/css/froala_editor.css
froala_editor/static/froala_editor/css/froala_editor.min.css
froala_editor/static/froala_editor/css/froala_editor.pkgd.css
froala_editor/static/froala_editor/css/froala_editor.pkgd.min.css
froala_editor/static/froala_editor/css/froala_style.css
froala_editor/static/froala_editor/css/froala_style.min.css
froala_editor/static/froala_editor/css/plugins.pkgd.css
froala_editor/static/froala_editor/css/plugins.pkgd.min.css
froala_editor/static/froala_editor/css/plugins/char_counter.css
froala_editor/static/froala_editor/css/plugins/char_counter.min.css
froala_editor/static/froala_editor/css/plugins/code_snippet.css
froala_editor/static/froala_editor/css/plugins/code_snippet.min.css
froala_editor/static/froala_editor/css/plugins/code_view.css
froala_editor/static/froala_editor/css/plugins/code_view.min.css
froala_editor/static/froala_editor/css/plugins/colors.css
froala_editor/static/froala_editor/css/plugins/colors.min.css
froala_editor/static/froala_editor/css/plugins/draggable.css
froala_editor/static/froala_editor/css/plugins/draggable.min.css
froala_editor/static/froala_editor/css/plugins/emoticons.css
froala_editor/static/froala_editor/css/plugins/emoticons.min.css
froala_editor/static/froala_editor/css/plugins/file.css
froala_editor/static/froala_editor/css/plugins/file.min.css
froala_editor/static/froala_editor/css/plugins/files_manager.css
froala_editor/static/froala_editor/css/plugins/files_manager.min.css
froala_editor/static/froala_editor/css/plugins/filestack.css
froala_editor/static/froala_editor/css/plugins/filestack.min.css
