Metadata-Version: 2.4
Name: django-froala-editor
Version: 5.0.0
Summary: django-froala-editor package helps integrate Froala WYSIWYG HTML editor with Django.
Home-page: http://github.com/froala/django-froala-editor/
Author: Dipesh Acharya
Author-email: dipesh@awecode.com
Maintainer: Froala Labs
License: BSD License
Keywords: froala,django,admin,wysiwyg,editor,text,html,editor,rich,web
Classifier: Environment :: Web Environment
Classifier: Framework :: Django
Classifier: Intended Audience :: Developers
Classifier: License :: OSI Approved :: BSD License
Classifier: Operating System :: OS Independent
Classifier: Programming Language :: Python
Classifier: Programming Language :: Python :: 2.7
Classifier: Programming Language :: Python :: 3
Classifier: Topic :: Internet :: WWW/HTTP
Classifier: Topic :: Internet :: WWW/HTTP :: Dynamic Content
Dynamic: author
Dynamic: author-email
Dynamic: classifier
Dynamic: description
Dynamic: home-page
Dynamic: keywords
Dynamic: license
Dynamic: maintainer
Dynamic: summary
